docdata/__init__.py
docdata/api.py
docdata/py.typed
docdata/version.py
docdata-0.0.5.dist-info/licenses/LICENSE
docdata-0.0.5.dist-info/METADATA
docdata-0.0.5.dist-info/WHEEL
docdata-0.0.5.dist-info/top_level.txt
docdata-0.0.5.dist-info/RECORD
