Metadata-Version: 2.4
Name: docdata
Version: 0.0.5
Summary: Add structured information to the end of your python docstrings.
Author-email: Charles Tapley Hoyt <cthoyt@gmail.com>
Maintainer-email: Charles Tapley Hoyt <cthoyt@gmail.com>
License: MIT License
Project-URL: Bug Tracker, https://github.com/cthoyt/docdata/issues
Project-URL: Homepage, https://github.com/cthoyt/docdata
Project-URL: Repository, https://github.com/cthoyt/docdata.git
Project-URL: Documentation, https://docdata.readthedocs.io
Keywords: snekpack,cookiecutter
Classifier: Development Status :: 1 - Planning
Classifier: Environment :: Console
Classifier: Intended Audience :: Developers
Classifier: License :: OSI Approved :: MIT License
Classifier: Operating System :: OS Independent
Classifier: Framework :: Pytest
Classifier: Framework :: tox
Classifier: Framework :: Sphinx
Classifier: Programming Language :: Python
Classifier: Programming Language :: Python :: 3.9
Classifier: Programming Language :: Python :: 3.10
Classifier: Programming Language :: Python :: 3.11
Classifier: Programming Language :: Python :: 3.12
Classifier: Programming Language :: Python :: 3 :: Only
Requires-Python: >=3.9
License-File: LICENSE
Requires-Dist: pyyaml
Provides-Extra: tests
Requires-Dist: pytest; extra == "tests"
Requires-Dist: coverage; extra == "tests"
Provides-Extra: docs
Requires-Dist: sphinx<8; extra == "docs"
Requires-Dist: sphinx-rtd-theme; extra == "docs"
Requires-Dist: sphinx_automodapi; extra == "docs"
Dynamic: license-file
